ini_cfg_parser/__init__.py
ini_cfg_parser/ini_cfg_parser.py
tests/__init__.py
tests/test_ini_parser.py
ini_cfg_parser-0.1.9.dist-info/LICENSE
ini_cfg_parser-0.1.9.dist-info/METADATA
ini_cfg_parser-0.1.9.dist-info/WHEEL
ini_cfg_parser-0.1.9.dist-info/entry_points.txt
ini_cfg_parser-0.1.9.dist-info/top_level.txt
ini_cfg_parser-0.1.9.dist-info/RECORD
