Metadata-Version: 2.1
Name: ini_cfg_parser
Version: 0.1.9
Summary: Parser for ini files
Home-page: https://github.com/pukkunk/ini_cfg_parser
Author: pukkunk
Classifier: Programming Language :: Python :: 3
Requires-Python: >=3.8
License-File: LICENSE
